{
  "couleur0": [
    {
      "desc": "Sortie de la zone de départ",
      "id": 1,
      "points": 10,
      "priorite": 1,
      "taches": [
        {
          "desc": "sortie de la zone de départ vers objetif 1",
          "id": 1,
          "positionX": 1000,
          "positionY": 870,
          "dist": 0,
          "type": "deplacement",
          "subtype": "goto",
          "actionId": -1,
          "mirror": "MIRRORY"
        }
      ]
    },
    {
      "desc": "Bloc zone de départ",
      "id": 2,
      "points": 5,
      "priorite": 1,
      "taches": [
        {
          "desc": "go position cube départ",
          "id": 1,
          "positionX": 1000,
          "positionY": 850,
          "dist": 0,
          "type": "deplacement",
          "subtype": "goto",
          "actionId": -1,
          "mirror": "MIRRORY"
        },
        {
          "desc": "déplacement bloc zone de départ",
          "id": 2,
          "positionX": 300,
          "positionY": 850,
          "dist": 0,
          "type": "deplacement",
          "subtype": "goto",
          "actionId": -1,
          "mirror": "MIRRORY"
        },
        {
          "desc": "On recule pour se dégager",
          "id": 3,
          "positionX": 0,
          "positionY": 0,
          "dist": -200,
          "type": "deplacement",
          "subtype": "go",
          "actionId": -1,
          "mirror": "MIRRORY"
        }
      ]
    },
    {
      "desc": "Panneau domotik",
      "id": 3,
      "points": 25,
      "priorite": 1,
      "taches": [
        {
          "desc": "Go position panneau domotique",
          "id": 1,
          "positionX": 500,
          "positionY": 1130,
          "dist": 0,
          "type": "deplacement",
          "subtype": "goto",
          "actionId": -1,
          "mirror": "MIRRORY"
        },
        {
          "desc": "Alignement panneau domotique",
          "id": 2,
          "positionX": 0,
          "positionY": 1130,
          "dist": 0,
          "type": "deplacement",
          "subtype": "face",
          "actionId": -1,
          "mirror": "MIRRORY"
        },
        {
          "desc": "go position panneau domotique pour action",
          "id": 3,
          "positionX": 200,
          "positionY": 1130,
          "dist": 0,
          "type": "deplacement",
          "subtype": "goto",
          "actionId": -1,
          "mirror": "MIRRORY"
        },
        {
          "desc": "Préparation allumage interrupteur",
          "id": 4,
          "positionX": 0,
          "positionY": 0,
          "dist": 0,
          "type": "manipulation",
          "actionId": 12,
          "mirror": "MIRRORY"
        },
        {
          "desc": "Allumage interrupteur",
          "id": 5,
          "positionX": 0,
          "positionY": 0,
          "dist": 0,
          "type": "manipulation",
          "actionId": 13,
          "mirror": "MIRRORY"
        },
        {
          "desc": "On recule pour se dégager",
          "id": 6,
          "positionX": 0,
          "positionY": 0,
          "dist": -200,
          "type": "deplacement",
          "subtype": "go",
          "actionId": -1,
          "mirror": "MIRRORY"
        }
      ]
    },
    {
      "desc": "Abeille",
      "id": 4,
      "points": 50,
      "priorite": 1,
      "taches": [
        {
          "desc": "Go position séquence abeille",
          "id": 1,
          "positionX": 1800,
          "positionY": 219,
          "dist": 0,
          "type": "deplacement",
          "subtype": "goto",
          "actionId": -1,
          "mirror": "MIRRORY"
        },
        {
          "desc": "Alignement pour lancement abeille",
          "id": 2,
          "positionX": 1800,
          "positionY": 3000,
          "dist": 0,
          "type": "deplacement",
          "subtype": "face",
          "actionId": -1,
          "mirror": "MIRRORY"
        },
        {
          "desc": "Mise en position lancement abeille",
          "id": 3,
          "positionX": 1800,
          "positionY": 124,
          "dist": 0,
          "type": "deplacement",
          "subtype": "goto_back",
          "actionId": -1,
          "mirror": "MIRRORY"
        },
        {
          "desc": "Abaissement bras",
          "id": 4,
          "positionX": 0,
          "positionY": 0,
          "dist": 0,
          "type": "manipulation",
          "actionId": 1,
          "mirror": "SPECIFIC"
        },
        {
          "desc": "Lancement abeille",
          "id": 5,
          "positionX": 1800,
          "positionY": 334,
          "dist": 0,
          "type": "deplacement",
          "subtype": "goto",
          "actionId": -1,
          "mirror": "MIRRORY"
        },
        {
          "desc": "Rentrer bras",
          "id": 6,
          "positionX": 0,
          "positionY": 0,
          "dist": 0,
          "type": "manipulation",
          "actionId": 0,
          "mirror": "SPECIFIC"
        }
      ]
    },
    {
      "desc": "Eau propre",
      "id": 5,
      "points": 45,
      "priorite": 1,
      "taches": [
        {
          "desc": "Esquive cube de merde",
          "id": 1,
          "positionX": 1100,
          "positionY": 630,
          "dist": 0,
          "type": "deplacement",
          "subtype": "goto",
          "actionId": -1,
          "mirror": "MIRRORY"
        },
        {
          "desc": "Go position Eau propre",
          "id": 2,
          "positionX": 850,
          "positionY": 400,
          "dist": 0,
          "type": "deplacement",
          "subtype": "goto",
          "actionId": -1,
          "mirror": "MIRRORY"
        },
        {
          "desc": "Alignement Eau propre",
          "id": 3,
          "positionX": 850,
          "positionY": 0,
          "dist": 0,
          "type": "deplacement",
          "subtype": "face",
          "actionId": -1,
          "mirror": "MIRRORY"
        },
        {
          "desc": "Préparation remplissage",
          "id": 4,
          "positionX": 0,
          "positionY": 0,
          "dist": 0,
          "type": "manipulation",
          "actionId": 10,
          "mirror": "MIRRORY"
        },
        {
          "desc": "Mise en position pour récupération Eau propre",
          "id": 5,
          "positionX": 850,
          "positionY": 225,
          "dist": 0,
          "type": "deplacement",
          "subtype": "goto",
          "actionId": -1,
          "mirror": "SPECIFIC"
        },
        {
          "desc": "Remplissage",
          "id": 6,
          "positionX": 0,
          "positionY": 0,
          "dist": 0,
          "type": "manipulation",
          "actionId": 9,
          "mirror": "MIRRORY"
        },
        {
          "desc": "On se dégage",
          "id": 7,
          "positionX": 0,
          "positionY": 0,
          "dist": -200,
          "type": "deplacement",
          "subtype": "go",
          "actionId": -1,
          "mirror": "MIRRORY"
        },
        {
          "desc": "Remplissage rangement",
          "id": 8,
          "positionX": 0,
          "positionY": 0,
          "dist": 0,
          "type": "manipulation",
          "actionId": 11,
          "mirror": "MIRRORY"
        },
        {
          "desc": "Go pré-position lancement Eau propre",
          "id": 9,
          "positionX": 200,
          "positionY": 1130,
          "dist": 0,
          "type": "deplacement",
          "subtype": "goto",
          "actionId": -1,
          "mirror": "MIRRORY"
        },
        {
          "desc": "Go pré-position lancement Eau propre",
          "id": 10,
          "positionX": 200,
          "positionY": 750,
          "dist": 0,
          "type": "deplacement",
          "subtype": "goto",
          "actionId": -1,
          "mirror": "MIRRORY"
        },
        {
          "desc": "Go position lancement Eau propre",
          "id": 11,
          "positionX": 220,
          "positionY": 930,
          "dist": 0,
          "type": "deplacement",
          "subtype": "goto_back",
          "actionId": -1,
          "mirror": "MIRRORY"
        },
        {
          "desc": "Alignement lancement Eau propre",
          "id": 12,
          "positionX": 720,
          "positionY": 1793,
          "dist": 0,
          "type": "deplacement",
          "subtype": "face",
          "actionId": -1,
          "mirror": "SPECIFIC"
        },
        {
          "desc": "Lancement de l\u0027eau propre",
          "id": 13,
          "positionX": 0,
          "positionY": 0,
          "dist": 0,
          "type": "manipulation",
          "actionId": 4,
          "mirror": "MIRRORY"
        }
      ]
    }
  ],
  "couleur3000": [
    {
      "desc": "Sortie de la zone de départ",
      "id": 1,
      "points": 10,
      "priorite": 1,
      "taches": [
        {
          "desc": "sortie de la zone de départ vers objetif 1",
          "id": 1,
          "positionX": 1000,
          "positionY": 2130,
          "dist": 0,
          "type": "deplacement",
          "subtype": "goto",
          "actionId": -1,
          "mirror": "MIRRORY"
        }
      ]
    },
    {
      "desc": "Bloc zone de départ",
      "id": 2,
      "points": 5,
      "priorite": 1,
      "taches": [
        {
          "desc": "go position cube départ",
          "id": 1,
          "positionX": 1000,
          "positionY": 2150,
          "dist": 0,
          "type": "deplacement",
          "subtype": "goto",
          "actionId": -1,
          "mirror": "MIRRORY"
        },
        {
          "desc": "déplacement bloc zone de départ",
          "id": 2,
          "positionX": 300,
          "positionY": 2150,
          "dist": 0,
          "type": "deplacement",
          "subtype": "goto",
          "actionId": -1,
          "mirror": "MIRRORY"
        },
        {
          "desc": "On recule pour se dégager",
          "id": 3,
          "positionX": 0,
          "positionY": 3000,
          "dist": -200,
          "type": "deplacement",
          "subtype": "go",
          "actionId": -1,
          "mirror": "MIRRORY"
        }
      ]
    },
    {
      "desc": "Panneau domotik",
      "id": 3,
      "points": 25,
      "priorite": 1,
      "taches": [
        {
          "desc": "Go position panneau domotique",
          "id": 1,
          "positionX": 500,
          "positionY": 1870,
          "dist": 0,
          "type": "deplacement",
          "subtype": "goto",
          "actionId": -1,
          "mirror": "MIRRORY"
        },
        {
          "desc": "Alignement panneau domotique",
          "id": 2,
          "positionX": 0,
          "positionY": 1870,
          "dist": 0,
          "type": "deplacement",
          "subtype": "face",
          "actionId": -1,
          "mirror": "MIRRORY"
        },
        {
          "desc": "go position panneau domotique pour action",
          "id": 3,
          "positionX": 200,
          "positionY": 1870,
          "dist": 0,
          "type": "deplacement",
          "subtype": "goto",
          "actionId": -1,
          "mirror": "MIRRORY"
        },
        {
          "desc": "Préparation allumage interrupteur",
          "id": 4,
          "positionX": 0,
          "positionY": 3000,
          "dist": 0,
          "type": "manipulation",
          "actionId": 12,
          "mirror": "MIRRORY"
        },
        {
          "desc": "Allumage interrupteur",
          "id": 5,
          "positionX": 0,
          "positionY": 3000,
          "dist": 0,
          "type": "manipulation",
          "actionId": 13,
          "mirror": "MIRRORY"
        },
        {
          "desc": "On recule pour se dégager",
          "id": 6,
          "positionX": 0,
          "positionY": 3000,
          "dist": -200,
          "type": "deplacement",
          "subtype": "go",
          "actionId": -1,
          "mirror": "MIRRORY"
        }
      ]
    },
    {
      "desc": "Abeille",
      "id": 4,
      "points": 50,
      "priorite": 1,
      "taches": [
        {
          "desc": "Go position séquence abeille",
          "id": 1,
          "positionX": 1800,
          "positionY": 2781,
          "dist": 0,
          "type": "deplacement",
          "subtype": "goto",
          "actionId": -1,
          "mirror": "MIRRORY"
        },
        {
          "desc": "Alignement pour lancement abeille",
          "id": 2,
          "positionX": 1800,
          "positionY": 0,
          "dist": 0,
          "type": "deplacement",
          "subtype": "face",
          "actionId": -1,
          "mirror": "MIRRORY"
        },
        {
          "desc": "Mise en position lancement abeille",
          "id": 3,
          "positionX": 1800,
          "positionY": 2876,
          "dist": 0,
          "type": "deplacement",
          "subtype": "goto_back",
          "actionId": -1,
          "mirror": "MIRRORY"
        },
        {
          "desc": "Abaissement bras",
          "id": 4,
          "positionX": 0,
          "positionY": 0,
          "dist": 0,
          "type": "manipulation",
          "actionId": 3,
          "mirror": "SPECIFIC"
        },
        {
          "desc": "Lancement abeille",
          "id": 5,
          "positionX": 1800,
          "positionY": 2666,
          "dist": 0,
          "type": "deplacement",
          "subtype": "goto",
          "actionId": -1,
          "mirror": "MIRRORY"
        },
        {
          "desc": "Rentrer bras",
          "id": 6,
          "positionX": 0,
          "positionY": 0,
          "dist": 0,
          "type": "manipulation",
          "actionId": 2,
          "mirror": "SPECIFIC"
        }
      ]
    },
    {
      "desc": "Eau propre",
      "id": 5,
      "points": 45,
      "priorite": 1,
      "taches": [
        {
          "desc": "Esquive cube de merde",
          "id": 1,
          "positionX": 1100,
          "positionY": 2370,
          "dist": 0,
          "type": "deplacement",
          "subtype": "goto",
          "actionId": -1,
          "mirror": "MIRRORY"
        },
        {
          "desc": "Go position Eau propre",
          "id": 2,
          "positionX": 850,
          "positionY": 2600,
          "dist": 0,
          "type": "deplacement",
          "subtype": "goto",
          "actionId": -1,
          "mirror": "MIRRORY"
        },
        {
          "desc": "Alignement Eau propre",
          "id": 3,
          "positionX": 850,
          "positionY": 3000,
          "dist": 0,
          "type": "deplacement",
          "subtype": "face",
          "actionId": -1,
          "mirror": "MIRRORY"
        },
        {
          "desc": "Préparation remplissage",
          "id": 4,
          "positionX": 0,
          "positionY": 3000,
          "dist": 0,
          "type": "manipulation",
          "actionId": 10,
          "mirror": "MIRRORY"
        },
        {
          "desc": "Mise en position pour récupération Eau propre",
          "id": 5,
          "positionX": 850,
          "positionY": 2785,
          "dist": 0,
          "type": "deplacement",
          "subtype": "goto",
          "actionId": -1,
          "mirror": "SPECIFIC"
        },
        {
          "desc": "Remplissage",
          "id": 6,
          "positionX": 0,
          "positionY": 3000,
          "dist": 0,
          "type": "manipulation",
          "actionId": 9,
          "mirror": "MIRRORY"
        },
        {
          "desc": "On se dégage",
          "id": 7,
          "positionX": 0,
          "positionY": 3000,
          "dist": -200,
          "type": "deplacement",
          "subtype": "go",
          "actionId": -1,
          "mirror": "MIRRORY"
        },
        {
          "desc": "Remplissage rangement",
          "id": 8,
          "positionX": 0,
          "positionY": 3000,
          "dist": 0,
          "type": "manipulation",
          "actionId": 11,
          "mirror": "MIRRORY"
        },
        {
          "desc": "Go pré-position lancement Eau propre",
          "id": 9,
          "positionX": 200,
          "positionY": 1870,
          "dist": 0,
          "type": "deplacement",
          "subtype": "goto",
          "actionId": -1,
          "mirror": "MIRRORY"
        },
        {
          "desc": "Go pré-position lancement Eau propre",
          "id": 10,
          "positionX": 200,
          "positionY": 2250,
          "dist": 0,
          "type": "deplacement",
          "subtype": "goto",
          "actionId": -1,
          "mirror": "MIRRORY"
        },
        {
          "desc": "Go position lancement Eau propre",
          "id": 11,
          "positionX": 220,
          "positionY": 2070,
          "dist": 0,
          "type": "deplacement",
          "subtype": "goto_back",
          "actionId": -1,
          "mirror": "MIRRORY"
        },
        {
          "desc": "Alignement lancement Eau propre",
          "id": 12,
          "positionX": 2000,
          "positionY": 130,
          "dist": 0,
          "type": "deplacement",
          "subtype": "face",
          "actionId": -1,
          "mirror": "SPECIFIC"
        },
        {
          "desc": "Lancement de l\u0027eau propre",
          "id": 13,
          "positionX": 0,
          "positionY": 3000,
          "dist": 0,
          "type": "manipulation",
          "actionId": 4,
          "mirror": "MIRRORY"
        }
      ]
    }
  ]
}
